einky-0.0.4.dist-info/DESCRIPTION.rst
einky-0.0.4.dist-info/METADATA
einky-0.0.4.dist-info/RECORD
einky-0.0.4.dist-info/WHEEL
einky-0.0.4.dist-info/metadata.json
einky-0.0.4.dist-info/top_level.txt
inky/__init__.py
inky/eeprom.py
inky/inky.py
inky/phat.py
inky/what.py
